reid_hota/__init__.py
reid_hota/config.py
reid_hota/cost_matrix.py
reid_hota/hota_data.py
reid_hota/hota_errors.py
reid_hota/hota_utils.py
reid_hota/reid_hota.py
reid_hota/sparse_matrix.py
reid_hota-0.2.1.dist-info/METADATA
reid_hota-0.2.1.dist-info/WHEEL
reid_hota-0.2.1.dist-info/licenses/LICENSE
reid_hota-0.2.1.dist-info/RECORD
