Metadata-Version: 2.4
Name: reid_hota
Version: 0.2.1
Summary: Modified HOTA (Higher Order Tracking Accuracy) extended for ReID evaluation
Project-URL: Homepage, https://github.com/usnistgov/reid_hota
Author-email: Michael Majurski <michael.majurski@nist.gov>
License-File: LICENSE
Requires-Python: >=3.10
Requires-Dist: numpy>=2.2.6
Requires-Dist: pandas>=2.2.3
Requires-Dist: pyarrow>=20.0.0
Requires-Dist: scipy>=1.15.3
